moviebox_api/__init__.py
moviebox_api/__main__.py
moviebox_api/_bases.py
moviebox_api/constants.py
moviebox_api/core.py
moviebox_api/download.py
moviebox_api/exceptions.py
moviebox_api/helpers.py
moviebox_api/models.py
moviebox_api/py.typed
moviebox_api/requests.py
moviebox_api/stream.py
moviebox_api/cli/__init__.py
moviebox_api/cli/__main__.py
moviebox_api/cli/downloader.py
moviebox_api/cli/extras.py
moviebox_api/cli/helpers.py
moviebox_api/cli/interactive.py
moviebox_api/cli/interface.py
moviebox_api/extractor/__init__.py
moviebox_api/extractor/_core.py
moviebox_api/extractor/exceptions.py
moviebox_api/extractor/helpers.py
moviebox_api/extractor/models/__init__.py
moviebox_api/extractor/models/json.py
moviebox_api/extractor/models/tag.py
moviebox_api/extras/__init__.py
moviebox_api/extras/auto.py
moviebox_api-0.3.4.post3.dist-info/METADATA
moviebox_api-0.3.4.post3.dist-info/WHEEL
moviebox_api-0.3.4.post3.dist-info/entry_points.txt
moviebox_api-0.3.4.post3.dist-info/licenses/LICENSE
moviebox_api-0.3.4.post3.dist-info/RECORD
