Metadata-Version: 2.4
Name: moviebox-api
Version: 0.3.4.post3
Summary: Unofficial wrapper for moviebox.ph - search, discover and download movies, tv-series and their subtitles.
Project-URL: homepage, https://github.com/Simatwa/moviebox-api
Project-URL: repository, https://github.com/Simatwa/moviebox-api
Project-URL: documentation, https://github.com/Simatwa/moviebox-api
Author-email: smartwa <smartwacaleb@gmail.com>
License-Expression: Unlicense
License-File: LICENSE
Classifier: Intended Audience :: Developers
Classifier: License :: OSI Approved :: The Unlicense (Unlicense)
Classifier: Operating System :: OS Independent
Classifier: Programming Language :: Python :: 3
Classifier: Programming Language :: Python :: 3.10
Classifier: Programming Language :: Python :: 3.11
Classifier: Programming Language :: Python :: 3.12
Classifier: Programming Language :: Python :: 3.13
Classifier: Programming Language :: Python :: 3.14
Classifier: Topic :: Communications :: File Sharing
Requires-Python: >=3.10
Requires-Dist: bs4>=0.0.2
Requires-Dist: httpx>=0.28.1
Requires-Dist: pydantic>=2.11.7
Requires-Dist: throttlebuster>=0.1.11
Provides-Extra: cli
Requires-Dist: click>=8.2.1; extra == 'cli'
Requires-Dist: readline>=6.2.4.2; (sys_platform == 'win32') and extra == 'cli'
Requires-Dist: rich>=14.1.0; extra == 'cli'
